linux_mcp_toolkit/__init__.py
linux_mcp_toolkit/main.py
iflow_mcp_linux_mcp_toolkit-1.0.12.dist-info/METADATA
iflow_mcp_linux_mcp_toolkit-1.0.12.dist-info/WHEEL
iflow_mcp_linux_mcp_toolkit-1.0.12.dist-info/entry_points.txt
iflow_mcp_linux_mcp_toolkit-1.0.12.dist-info/top_level.txt
iflow_mcp_linux_mcp_toolkit-1.0.12.dist-info/RECORD
