Metadata-Version: 2.4
Name: iflow-mcp_linux-mcp-toolkit
Version: 1.0.12
Summary: Enhanced Linux MCP Toolkit with Interactive Shell Support
Author-email: Linux MCP Toolkit Team <contact@linuxmcp.com>
Project-URL: Homepage, https://github.com/linux-mcp/linux-mcp-toolkit
Project-URL: Bug Reports, https://github.com/linux-mcp/linux-mcp-toolkit/issues
Project-URL: Source, https://github.com/linux-mcp/linux-mcp-toolkit
Project-URL: Documentation, https://linux-mcp-toolkit.readthedocs.io
Keywords: linux,ssh,mcp,system-administration,remote-management,interactive-shell
Classifier: Development Status :: 4 - Beta
Classifier: Intended Audience :: Developers
Classifier: Intended Audience :: System Administrators
Classifier: License :: OSI Approved :: MIT License
Classifier: Operating System :: OS Independent
Classifier: Programming Language :: Python :: 3
Classifier: Programming Language :: Python :: 3.8
Classifier: Programming Language :: Python :: 3.9
Classifier: Programming Language :: Python :: 3.10
Classifier: Programming Language :: Python :: 3.11
Classifier: Programming Language :: Python :: 3.12
Classifier: Topic :: System :: Systems Administration
Classifier: Topic :: Software Development :: Libraries :: Python Modules
Requires-Python: >=3.8
Requires-Dist: paramiko>=2.7.0
Requires-Dist: mcp>=1.0.0
